pypi_description_test
