Metadata-Version: 2.1
Name: pypi-description-test
Version: 0.12
Summary: py_description_test
Home-page: UNKNOWN
Author: David Vitale
License: UNKNOWN
Platform: UNKNOWN
